gds_tools/__init__.py
gds_tools/classes.py
gds_tools/functions.py
gds_tools/geometry.py
gds_tools/heal.py
gds_tools/routing.py
gds_tools-0.1.2.dist-info/LICENSE
gds_tools-0.1.2.dist-info/METADATA
gds_tools-0.1.2.dist-info/WHEEL
gds_tools-0.1.2.dist-info/top_level.txt
gds_tools-0.1.2.dist-info/RECORD
